mansort/__init__.py
mansort/mansort.py
ManualSorter-0.1.2.dist-info/LICENSE
ManualSorter-0.1.2.dist-info/METADATA
ManualSorter-0.1.2.dist-info/WHEEL
ManualSorter-0.1.2.dist-info/top_level.txt
ManualSorter-0.1.2.dist-info/RECORD
